{
  "updated": "2026-07-17T13:54:49Z",
  "update_interval_hours": 6,
  "stations": [
    {
      "id": "BSCA1",
      "name": "BSCA1",
      "has_model": true,
      "has_realtime": false,
      "status": "historical_only",
      "current": null,
      "predictions": null,
      "model_type": "xgboost"
    },
    {
      "id": "CRTA1",
      "name": "CRTA1",
      "has_model": true,
      "has_realtime": false,
      "status": "historical_only",
      "current": null,
      "predictions": null,
      "model_type": "timesfm",
      "timesfm_benchmark": {
        "1d": {
          "auc_roc": 0.897,
          "mae": 0.78
        },
        "3d": {
          "auc_roc": 0.85,
          "mae": 0.89
        },
        "5d": {
          "auc_roc": 0.759,
          "mae": 0.96
        },
        "7d": {
          "auc_roc": 0.758,
          "mae": 1.04
        }
      },
      "n_days": 3362,
      "n_hyp_days": 48
    },
    {
      "id": "MBLA1",
      "name": "MBLA1",
      "has_model": true,
      "has_realtime": false,
      "status": "historical_only",
      "current": null,
      "predictions": null,
      "model_type": "xgboost"
    },
    {
      "id": "APQF1",
      "name": "APQF1",
      "has_model": true,
      "has_realtime": false,
      "status": "historical_only",
      "current": null,
      "predictions": null,
      "model_type": "timesfm",
      "timesfm_benchmark": {
        "1d": {
          "auc_roc": 0.751,
          "mae": 1.13
        },
        "3d": {
          "auc_roc": 0.685,
          "mae": 1.35
        },
        "5d": {
          "auc_roc": 0.63,
          "mae": 1.45
        },
        "7d": {
          "auc_roc": 0.633,
          "mae": 1.52
        }
      },
      "n_days": 1258,
      "n_hyp_days": 77
    },
    {
      "id": "KATA1",
      "name": "KATA1",
      "has_model": true,
      "has_realtime": false,
      "status": "historical_only",
      "current": null,
      "predictions": null,
      "model_type": "xgboost"
    },
    {
      "id": "FRKF1",
      "name": "FRKF1",
      "has_model": true,
      "has_realtime": false,
      "status": "historical_only",
      "current": null,
      "predictions": null,
      "model_type": "timesfm",
      "timesfm_benchmark": {
        "1d": {
          "auc_roc": 0.832,
          "mae": 1.46,
          "correlation": 0.668
        },
        "3d": {
          "auc_roc": 0.73,
          "mae": 2.09,
          "correlation": 0.341
        },
        "5d": {
          "auc_roc": 0.579,
          "mae": 2.35,
          "correlation": 0.076
        },
        "7d": {
          "auc_roc": 0.41,
          "mae": 2.55,
          "correlation": -0.119
        }
      },
      "n_days": 616,
      "n_hyp_days": 160
    },
    {
      "id": "GBHM6",
      "name": "GBHM6",
      "has_model": true,
      "has_realtime": false,
      "status": "historical_only",
      "current": null,
      "predictions": null,
      "model_type": "xgboost"
    }
  ],
  "model_info": {
    "xgboost": {
      "description": "Station-specific XGBoost classifier with engineered features",
      "features": "DO lags, rolling stats, satellite SST/chlorophyll, cross-station deltas",
      "training": "Per-station with 70/30 temporal split"
    },
    "timesfm": {
      "description": "Google TimesFM 1.0 (200M params) zero-shot forecast",
      "approach": "Direct DO time-series forecasting with quantile uncertainty estimation",
      "note": "Used for stations with insufficient training events for XGBoost, excels on sparse-data stations",
      "benchmark": "AUC-ROC up to 0.91 on sparse stations where XGBoost fails (< 0.30)"
    }
  },
  "summary": {
    "total_stations": 7,
    "stations_with_models": 7,
    "stations_with_realtime": 0,
    "stations_with_data": 0,
    "stations_with_predictions": 0,
    "stations_with_warnings": 0
  }
}